{
    "tags": [
        {
            "desc": "retraC",
            "id": 2637849973,
            "user": "D00MD00MD00MD00M"
        },
        {
            "desc": "retraC",
            "id": 3017397862,
            "user": "erjaejerje"
        },
        {
            "desc": "<font color='#ff0000'>i </font><font color='#ff1000'>a</font><font color='#ff1100'>m</font><font color='#ff1200'> w</font><font color='#ff1300'>a</font><font color='#ff1400'>n</font><font color='#ff1500'>t</font><font color='#ff1600'>e</font><font color='#ff1700'>d </font><font color='#ff1800'>b</font><font color='#ff1900'>y </font><font color='#ff1a00'>t</font><font color='#ff1b00'>h</font><font color='#ff1c00'>e </font><font color='#ff1d00'>\u56fd</font><font color='#ff1e00'>\u5bb6</font><font color='#ff1f00'>\u5b89</font><font color='#ff2000'>\u5168</font><font color='#ff2100'>\u90e8</font>",
            "id": 3017404342,
            "user": "ektektktaekt"
        },
        {
            "desc": "splash",
            "id": 2263714442,
            "user": "embgred"

        }
    ]
}
